mondriaan/__init__.py
mondriaan/example.py
mondriaan/forecaster.py
mondriaan-0.1.dist-info/LICENSE
mondriaan-0.1.dist-info/METADATA
mondriaan-0.1.dist-info/WHEEL
mondriaan-0.1.dist-info/entry_points.txt
mondriaan-0.1.dist-info/top_level.txt
mondriaan-0.1.dist-info/RECORD
