Metadata-Version: 2.1
Name: mondriaan
Version: 0.1
Summary: A time-series forecasting python package
Home-page: https://github.com/naftalic/mondriaan
Author: Naftali Cohen
Author-email: naftalic@gmail.com
License: MIT
Platform: UNKNOWN
Classifier: License :: OSI Approved :: MIT License
Classifier: Programming Language :: Python :: 3
Classifier: Programming Language :: Python :: 3.7
Requires-Dist: requests
